aydie_dataset_cleaner/__init__.py
aydie_dataset_cleaner/cleaner.py
aydie_dataset_cleaner/file_loader.py
aydie_dataset_cleaner/reporter.py
aydie_dataset_cleaner/utils.py
aydie_dataset_cleaner/validator.py
aydie_dataset_cleaner-1.0.0.dist-info/licenses/LICENSE
examples/example_usage.py
aydie_dataset_cleaner-1.0.0.dist-info/METADATA
aydie_dataset_cleaner-1.0.0.dist-info/WHEEL
aydie_dataset_cleaner-1.0.0.dist-info/top_level.txt
aydie_dataset_cleaner-1.0.0.dist-info/RECORD
