Metadata-Version: 2.4
Name: aydie-dataset-cleaner
Version: 1.0.0
Summary: A Python library to validate, profile, and clean datasets (CSV, Excel, Parquet) for machine learning workflows.
Author-email: "Aditya (Aydie) Dinesh K" <developer@aydie.in>
Project-URL: Homepage, https://opensource.aydie.in/
Project-URL: Bug Tracker, https://github.com/aydiegithub/aydie-dataset-cleaner/issues
Project-URL: Documentation, https://github.com/aydiegithub/aydie-dataset-cleaner#readme
Project-URL: Source, https://github.com/aydiegithub/aydie-dataset-cleaner
Keywords: dataset,cleaning,validation,ML,data-science,parquet,csv,excel
Classifier: Programming Language :: Python :: 3
Classifier: License :: OSI Approved :: MIT License
Classifier: Operating System :: OS Independent
Classifier: Topic :: Software Development :: Libraries :: Python Modules
Classifier: Intended Audience :: Developers
Classifier: Intended Audience :: Science/Research
Requires-Python: >=3.8
License-File: LICENSE
Requires-Dist: pandas>=1.5.0
Requires-Dist: numpy>=1.23.0
Requires-Dist: openpyxl
Requires-Dist: pyarrow
Requires-Dist: scikit-learn
Requires-Dist: jinja2
Dynamic: license-file
